pylon_pathfind/__init__.py
pylon_pathfind/example.py
pylon_pathfind/pathfinder.py
pylon_pathfind/data/demo_gauteng.json
pylon_pathfind-0.1.0.dist-info/METADATA
pylon_pathfind-0.1.0.dist-info/WHEEL
pylon_pathfind-0.1.0.dist-info/RECORD
