Metadata-Version: 2.4
Name: pylon_pathfind
Version: 0.1.0
Summary: Weather-aware pathfinding for a mobile solar-car strategy system
Project-URL: Homepage, https://example.com/pylon_pathfind
Author: RJ PRJ Group 5
Requires-Python: >=3.9
Requires-Dist: networkx>=3.2
